{
  "project_info": {
    "project_number": "976909370664",
    "firebase_url": "https://jugada-superliga.firebaseio.com",
    "project_id": "jugada-superliga",
    "storage_bucket": "jugada-superliga.appspot.com"
  },
  "client": [
    {
      "client_info": {
        "mobilesdk_app_id": "1:976909370664:android:3bb0dd03b803c7b4",
        "android_client_info": {
          "package_name": "com.balltoball.jugadasuperliga"
        }
      },
      "oauth_client": [
        {
          "client_id": "976909370664-ekingj0102s5adll3tmatufutjgrqq12.apps.googleusercontent.com",
          "client_type": 3
        }
      ],
      "api_key": [
        {
          "current_key": "AIzaSyDGge1W06LB_YbeMWZjhE9f9GkzU1HQNKk"
        }
      ],
      "services": {
        "appinvite_service": {
          "other_platform_oauth_client": [
            {
              "client_id": "976909370664-ekingj0102s5adll3tmatufutjgrqq12.apps.googleusercontent.com",
              "client_type": 3
            },
            {
              "client_id": "976909370664-siaae1mh2iimqn2fnmqpc8uvfbg9jtbi.apps.googleusercontent.com",
              "client_type": 2,
              "ios_info": {
                "bundle_id": "com.balltoball.jugadasuperliga"
              }
            }
          ]
        }
      }
    }
  ],
  "configuration_version": "1"
}